stv_lebanon/__init__.py
stv_lebanon/cli_interface.py
stv_lebanon/lambda_function.py
stv_lebanon/samples/Candidates.csv
stv_lebanon/samples/Groups.csv
stv_lebanon/samples/Votes.csv
stv_lebanon/samples/__init__.py
stv_lebanon/stv.py
stv_lebanon/stv_progress.py
stv_lebanon-0.99.3.dist-info/entry_points.txt
stv_lebanon-0.99.3.dist-info/LICENSE
stv_lebanon-0.99.3.dist-info/WHEEL
stv_lebanon-0.99.3.dist-info/METADATA
stv_lebanon-0.99.3.dist-info/RECORD
